limes/__init__.py
limes/config.py
limes/limes.py
limes/coms/__init__.py
limes/coms/requester.py
limes/coms/server.py
limes/models/__init__.py
limes/models/basic.py
limes/models/inventory.py
limes/models/network.py
limes/models/provider.py
limes/models/serializable.py
limes/tools/__init__.py
limes/tools/crytography.py
limes/tools/qol.py
limes_common-0.1.dev4.dist-info/LICENSE
limes_common-0.1.dev4.dist-info/METADATA
limes_common-0.1.dev4.dist-info/WHEEL
limes_common-0.1.dev4.dist-info/top_level.txt
limes_common-0.1.dev4.dist-info/RECORD
